README.rst
bin/dpline
dpline/__init__.py
dpline/main.py
dpline.egg-info/PKG-INFO
dpline.egg-info/SOURCES.txt
dpline.egg-info/dependency_links.txt
dpline.egg-info/top_level.txt