Metadata-Version: 1.1
Name: dpline
Version: 1.3
Summary: tool to remove duplicate lines from file
Home-page: https://github.com/dslackw/dpline
Author: dslackw
Author-email: d.zlatanidis@gmail.com
License: UNKNOWN
Keywords: unique,duplicate,text,lines
Platform: UNKNOWN
Classifier: Classifier: Development Status :: 3 - Alpha
Classifier: Classifier: Environment :: Console
Classifier: License :: OSI Approved :: GNU General Public License v3 (GPLv3)
Classifier: Classifier: Operating System :: POSIX
Classifier: Classifier: Operating System :: POSIX :: Linux
Classifier: Classifier: Operating System :: Unix
Classifier: Classifier: Programming Language :: Python
Classifier: Classifier: Programming Language :: Python :: 2
Classifier: Classifier: Programming Language :: Python :: 3
Classifier: Classifier: Topic :: Text Processing :: Filters
Classifier: Classifier: Topic :: Text Processing :: General
